pyglove/__init__.py
pyglove/core/__init__.py
pyglove/core/logging.py
pyglove/core/logging_test.py
pyglove/core/coding/__init__.py
pyglove/core/coding/errors.py
pyglove/core/coding/errors_test.py
pyglove/core/coding/execution.py
pyglove/core/coding/execution_test.py
pyglove/core/coding/function_generation.py
pyglove/core/coding/function_generation_test.py
pyglove/core/coding/parsing.py
pyglove/core/coding/parsing_test.py
pyglove/core/coding/permissions.py
pyglove/core/coding/permissions_test.py
pyglove/core/detouring/__init__.py
pyglove/core/detouring/class_detour.py
pyglove/core/detouring/class_detour_test.py
pyglove/core/geno/__init__.py
pyglove/core/geno/base.py
pyglove/core/geno/base_test.py
pyglove/core/geno/categorical.py
pyglove/core/geno/categorical_test.py
pyglove/core/geno/custom.py
pyglove/core/geno/custom_test.py
pyglove/core/geno/deduping.py
pyglove/core/geno/deduping_test.py
pyglove/core/geno/dna_generator.py
pyglove/core/geno/dna_generator_test.py
pyglove/core/geno/numerical.py
pyglove/core/geno/numerical_test.py
pyglove/core/geno/random.py
pyglove/core/geno/random_test.py
pyglove/core/geno/space.py
pyglove/core/geno/space_test.py
pyglove/core/geno/sweeping.py
pyglove/core/geno/sweeping_test.py
pyglove/core/hyper/__init__.py
pyglove/core/hyper/base.py
pyglove/core/hyper/categorical.py
pyglove/core/hyper/categorical_test.py
pyglove/core/hyper/custom.py
pyglove/core/hyper/custom_test.py
pyglove/core/hyper/derived.py
pyglove/core/hyper/derived_test.py
pyglove/core/hyper/dynamic_evaluation.py
pyglove/core/hyper/dynamic_evaluation_test.py
pyglove/core/hyper/evolvable.py
pyglove/core/hyper/evolvable_test.py
pyglove/core/hyper/iter.py
pyglove/core/hyper/iter_test.py
pyglove/core/hyper/numerical.py
pyglove/core/hyper/numerical_test.py
pyglove/core/hyper/object_template.py
pyglove/core/hyper/object_template_test.py
pyglove/core/io/__init__.py
pyglove/core/io/file_system.py
pyglove/core/io/file_system_test.py
pyglove/core/io/sequence.py
pyglove-0.4.5.dist-info/licenses/LICENSE
pyglove-0.4.5.dist-info/METADATA
pyglove-0.4.5.dist-info/WHEEL
pyglove-0.4.5.dist-info/top_level.txt
pyglove-0.4.5.dist-info/RECORD
