Metadata-Version: 2.4
Name: pyglove
Version: 0.4.5
Summary: PyGlove: A library for manipulating Python objects.
Home-page: https://github.com/google/pyglove
Author: PyGlove Authors
Author-email: pyglove-authors@google.com
License: Apache License 2.0
Keywords: ai machine learning automl mutable symbolic framework meta-programming
Classifier: Development Status :: 5 - Production/Stable
Classifier: Intended Audience :: Developers
Classifier: Intended Audience :: Education
Classifier: Intended Audience :: Science/Research
Classifier: License :: OSI Approved :: Apache Software License
Classifier: Programming Language :: Python :: 3
Classifier: Programming Language :: Python :: 3.9
Classifier: Topic :: Scientific/Engineering :: Artificial Intelligence
Classifier: Topic :: Scientific/Engineering :: Human Machine Interfaces
Classifier: Topic :: Software Development :: Code Generators
Classifier: Topic :: Software Development :: Libraries :: Python Modules
Classifier: Topic :: Software Development :: Libraries
License-File: LICENSE
Requires-Dist: docstring-parser>=0.12
Requires-Dist: termcolor>=1.1.0
Dynamic: author
Dynamic: author-email
Dynamic: classifier
Dynamic: description
Dynamic: description-content-type
Dynamic: home-page
Dynamic: keywords
Dynamic: license
Dynamic: license-file
Dynamic: requires-dist
Dynamic: summary
